pytest_mpi/__init__.py
pytest_mpi/_helpers.py
pytest_mpi/_version.py
pytest_mpi-0.6.dist-info/LICENSE.txt
pytest_mpi-0.6.dist-info/METADATA
pytest_mpi-0.6.dist-info/WHEEL
pytest_mpi-0.6.dist-info/entry_points.txt
pytest_mpi-0.6.dist-info/top_level.txt
pytest_mpi-0.6.dist-info/RECORD
