Metadata-Version: 1.1
Name: pytest-mpi
Version: 0.6
Summary: pytest plugin to collect information from tests
Home-page: https://pytest-mpi.readthedocs.io
Author: James Tocknell
Author-email: aragilar@gmail.com
License: 3-clause BSD
Keywords: pytest testing
Platform: UNKNOWN
Classifier: Framework :: Pytest
Classifier: Development Status :: 3 - Alpha
Classifier: Intended Audience :: Developers
Classifier: License :: OSI Approved :: BSD License
Classifier: Programming Language :: Python :: 3
Classifier: Programming Language :: Python :: 3.5
Classifier: Programming Language :: Python :: 3.6
Classifier: Programming Language :: Python :: 3.7
Classifier: Programming Language :: Python :: 3.8
Classifier: Programming Language :: Python :: 3.9
